setup.py
Evt/BinaryParser.py
Evt/Evt.py
Evt/__init__.py
Evt/lfle.py
Evt/mutablenamedtuple.py
python_evt.egg-info/PKG-INFO
python_evt.egg-info/SOURCES.txt
python_evt.egg-info/dependency_links.txt
python_evt.egg-info/top_level.txt