Metadata-Version: 1.0
Name: python-evt
Version: 0.1
Summary: Pure Python parser for classic Windows event log files (.evt).
Home-page: https://github.com/williballenthin/python-evt
Author: Willi Ballenthin
Author-email: willi.ballenthin@gmail.com
License: Apache 2.0 License
Platform: UNKNOWN
